Alexandria11/alex_mods.py
Alexandria11/data/GCE_Megan_2018.csv
Alexandria11/data/kepler_legacy_nissen_2017.csv
Alexandria11/data/st_ab_Megan_Spina_2018.csv
Alexandria11-0.1.dist-info/LICENSE
Alexandria11-0.1.dist-info/METADATA
Alexandria11-0.1.dist-info/WHEEL
Alexandria11-0.1.dist-info/top_level.txt
Alexandria11-0.1.dist-info/RECORD
