Metadata-Version: 2.1
Name: Alexandria11
Version: 0.1
Summary: Collection of tools to work with Galactic Archaeology
Home-page: https://github.com/ramstojh/Alexandria11
Author: Jhon Yana
Author-email: ramstojh@alumni.usp.br
License: MIT
Platform: UNKNOWN
License-File: LICENSE
Requires-Dist: numpy
Requires-Dist: pandas
Requires-Dist: tqdm
Requires-Dist: astropy
Requires-Dist: matplotlib
